uetai/__init__.py
uetai/version.py
uetai/logger/__init__.py
uetai/logger/base.py
uetai/logger/comet.py
uetai/utilities/__init__.py
uetai/utilities/imports.py
uetai-0.1.1.dist-info/LICENSE.txt
uetai-0.1.1.dist-info/METADATA
uetai-0.1.1.dist-info/WHEEL
uetai-0.1.1.dist-info/entry_points.txt
uetai-0.1.1.dist-info/top_level.txt
uetai-0.1.1.dist-info/RECORD
