Metadata-Version: 2.1
Name: uetai
Version: 0.1.1
Summary: UETAI is data validation and model debugger tools integrated with ML experiment tracking tools
Home-page: https://github.com/UETAILab/uetai
Author: UET AILab
Author-email: ailab@vnu.edu.vn
License: MIT
Project-URL: Bug Tracker, https://github.com/UETAILab/uetai/issues
Project-URL: Documentation, https://uetailab.github.io/uetai/
Project-URL: Source Code, https://github.com/UETAILab/uetai
Keywords: deep learning,AI
Platform: UNKNOWN
Classifier: Development Status :: 4 - Beta
Classifier: License :: OSI Approved :: MIT License
Classifier: Topic :: Scientific/Engineering :: Artificial Intelligence
Classifier: Programming Language :: Python :: 3 :: Only
Classifier: Programming Language :: Python :: 3.7
Classifier: Programming Language :: Python :: 3.8
Classifier: Programming Language :: Python :: 3.9
Requires-Python: >=3.7
Requires-Dist: torch (>=1.6)
Requires-Dist: numpy (>=1.14)
Requires-Dist: Pillow
Requires-Dist: comet-ml
Requires-Dist: pyyaml (>=5.4)
